[
  {
    "FilmCode": "Ilford Ortho%",
    "DeveloperCode": null,
    "FilmName": "Ilford Ortho Plus",
    "DeveloperName": "510-Pyro",
    "Dilution": "1+100",
    "ISO": "80",
    "Film35": "9",
    "Film120": "9",
    "Sheet": "9",
    "Temp": "20C",
    "NotesUrl": ""
  },
  {
    "FilmCode": "Ilford Ortho%",
    "DeveloperCode": null,
    "FilmName": "Ilford Ortho Plus",
    "DeveloperName": "Bellini DF2 Duo Step",
    "Dilution": "stock",
    "ISO": "160",
    "Film35": "3:30+3:30",
    "Film120": "3:30+3:30",
    "Sheet": "3:30+3:30",
    "Temp": "20C",
    "NotesUrl": ""
  },
  {
    "FilmCode": "Ilford Ortho%",
    "DeveloperCode": null,
    "FilmName": "Ilford Ortho Plus",
    "DeveloperName": "Bellini Hydrofen",
    "Dilution": "1+15",
    "ISO": "80",
    "Film35": "5",
    "Film120": "5",
    "Sheet": "5",
    "Temp": "20C",
    "NotesUrl": ""
  },
  {
    "FilmCode": "Ilford Ortho%",
    "DeveloperCode": null,
    "FilmName": "Ilford Ortho Plus",
    "DeveloperName": "Bellini Hydrofen",
    "Dilution": "1+31",
    "ISO": "80",
    "Film35": "10",
    "Film120": "10",
    "Sheet": "10",
    "Temp": "20C",
    "NotesUrl": ""
  },
  {
    "FilmCode": "Ilford Ortho%",
    "DeveloperCode": null,
    "FilmName": "Ilford Ortho Plus",
    "DeveloperName": "Black/White &amp; Green",
    "Dilution": "1+49",
    "ISO": "80",
    "Film35": "12:15",
    "Film120": "12:15",
    "Sheet": "12:15",
    "Temp": "20C",
    "NotesUrl": ""
  },
  {
    "FilmCode": "Ilford Ortho%",
    "DeveloperCode": null,
    "FilmName": "Ilford Ortho Plus",
    "DeveloperName": "Caffenol",
    "Dilution": "stock",
    "ISO": "80",
    "Film35": "8",
    "Film120": "8",
    "Sheet": "8",
    "Temp": "20C",
    "NotesUrl": ""
  },
  {
    "FilmCode": "Ilford Ortho%",
    "DeveloperCode": null,
    "FilmName": "Ilford Ortho Plus",
    "DeveloperName": "D-76",
    "Dilution": "stock",
    "ISO": "40",
    "Film35": "8",
    "Film120": "8",
    "Sheet": "8",
    "Temp": "20C",
    "NotesUrl": "<a href=\"devchart.php?devrow=2399\">[notes]</a>"
  },
  {
    "FilmCode": "Ilford Ortho%",
    "DeveloperCode": null,
    "FilmName": "Ilford Ortho Plus",
    "DeveloperName": "D-76",
    "Dilution": "1+1",
    "ISO": "40",
    "Film35": "10:30",
    "Film120": "10:30",
    "Sheet": "10:30",
    "Temp": "20C",
    "NotesUrl": "<a href=\"devchart.php?devrow=2400\">[notes]</a>"
  },
  {
    "FilmCode": "Ilford Ortho%",
    "DeveloperCode": null,
    "FilmName": "Ilford Ortho Plus",
    "DeveloperName": "D-76",
    "Dilution": "1+3",
    "ISO": "40",
    "Film35": "16",
    "Film120": "16",
    "Sheet": "16",
    "Temp": "20C",
    "NotesUrl": "<a href=\"devchart.php?devrow=2401\">[notes]</a>"
  },
  {
    "FilmCode": "Ilford Ortho%",
    "DeveloperCode": null,
    "FilmName": "Ilford Ortho Plus",
    "DeveloperName": "D-76",
    "Dilution": "stock",
    "ISO": "80",
    "Film35": "8",
    "Film120": "8",
    "Sheet": "8",
    "Temp": "20C",
    "NotesUrl": "<a href=\"devchart.php?devrow=14151\">[notes]</a>"
  },
  {
    "FilmCode": "Ilford Ortho%",
    "DeveloperCode": null,
    "FilmName": "Ilford Ortho Plus",
    "DeveloperName": "D-76",
    "Dilution": "1+1",
    "ISO": "80",
    "Film35": "10:30",
    "Film120": "10:30",
    "Sheet": "10:30",
    "Temp": "20C",
    "NotesUrl": "<a href=\"devchart.php?devrow=14143\">[notes]</a>"
  },
  {
    "FilmCode": "Ilford Ortho%",
    "DeveloperCode": null,
    "FilmName": "Ilford Ortho Plus",
    "DeveloperName": "D-76",
    "Dilution": "1+3",
    "ISO": "80",
    "Film35": "16",
    "Film120": "16",
    "Sheet": "16",
    "Temp": "20C",
    "NotesUrl": "<a href=\"devchart.php?devrow=14150\">[notes]</a>"
  },
  {
    "FilmCode": "Ilford Ortho%",
    "DeveloperCode": null,
    "FilmName": "Ilford Ortho Plus",
    "DeveloperName": "Diafine",
    "Dilution": "stock",
    "ISO": "160",
    "Film35": "3:30+3:30",
    "Film120": "3:30+3:30",
    "Sheet": "3:30+3:30",
    "Temp": "20C",
    "NotesUrl": ""
  },
  {
    "FilmCode": "Ilford Ortho%",
    "DeveloperCode": null,
    "FilmName": "Ilford Ortho Plus",
    "DeveloperName": "DK-50",
    "Dilution": "1+1",
    "ISO": "80",
    "Film35": "6:30",
    "Film120": "6:30",
    "Sheet": "6:30",
    "Temp": "20C",
    "NotesUrl": ""
  },
  {
    "FilmCode": "Ilford Ortho%",
    "DeveloperCode": null,
    "FilmName": "Ilford Ortho Plus",
    "DeveloperName": "EXG1",
    "Dilution": "stock",
    "ISO": "80",
    "Film35": "11",
    "Film120": "11",
    "Sheet": "11",
    "Temp": "21C",
    "NotesUrl": ""
  },
  {
    "FilmCode": "Ilford Ortho%",
    "DeveloperCode": null,
    "FilmName": "Ilford Ortho Plus",
    "DeveloperName": "HC-110",
    "Dilution": "B",
    "ISO": "80",
    "Film35": "6",
    "Film120": "6",
    "Sheet": "6",
    "Temp": "20C",
    "NotesUrl": "<a href=\"devchart.php?devrow=14552\">[notes]</a>"
  },
  {
    "FilmCode": "Ilford Ortho%",
    "DeveloperCode": null,
    "FilmName": "Ilford Ortho Plus",
    "DeveloperName": "HC-110",
    "Dilution": "B",
    "ISO": "80",
    "Film35": "8",
    "Film120": "8",
    "Sheet": "8",
    "Temp": "20C",
    "NotesUrl": "<a href=\"devchart.php?devrow=14498\">[notes]</a>"
  },
  {
    "FilmCode": "Ilford Ortho%",
    "DeveloperCode": null,
    "FilmName": "Ilford Ortho Plus",
    "DeveloperName": "ID-11",
    "Dilution": "stock",
    "ISO": "40",
    "Film35": "8",
    "Film120": "8",
    "Sheet": "8",
    "Temp": "20C",
    "NotesUrl": "<a href=\"devchart.php?devrow=2402\">[notes]</a>"
  },
  {
    "FilmCode": "Ilford Ortho%",
    "DeveloperCode": null,
    "FilmName": "Ilford Ortho Plus",
    "DeveloperName": "ID-11",
    "Dilution": "1+1",
    "ISO": "40",
    "Film35": "10:30",
    "Film120": "10:30",
    "Sheet": "10:30",
    "Temp": "20C",
    "NotesUrl": "<a href=\"devchart.php?devrow=2403\">[notes]</a>"
  },
  {
    "FilmCode": "Ilford Ortho%",
    "DeveloperCode": null,
    "FilmName": "Ilford Ortho Plus",
    "DeveloperName": "ID-11",
    "Dilution": "1+3",
    "ISO": "40",
    "Film35": "16",
    "Film120": "16",
    "Sheet": "16",
    "Temp": "20C",
    "NotesUrl": "<a href=\"devchart.php?devrow=2404\">[notes]</a>"
  },
  {
    "FilmCode": "Ilford Ortho%",
    "DeveloperCode": null,
    "FilmName": "Ilford Ortho Plus",
    "DeveloperName": "ID-11",
    "Dilution": "stock",
    "ISO": "80",
    "Film35": "8",
    "Film120": "8",
    "Sheet": "8",
    "Temp": "20C",
    "NotesUrl": "<a href=\"devchart.php?devrow=14154\">[notes]</a>"
  },
  {
    "FilmCode": "Ilford Ortho%",
    "DeveloperCode": null,
    "FilmName": "Ilford Ortho Plus",
    "DeveloperName": "ID-11",
    "Dilution": "1+1",
    "ISO": "80",
    "Film35": "10:30",
    "Film120": "10:30",
    "Sheet": "10:30",
    "Temp": "20C",
    "NotesUrl": "<a href=\"devchart.php?devrow=14152\">[notes]</a>"
  },
  {
    "FilmCode": "Ilford Ortho%",
    "DeveloperCode": null,
    "FilmName": "Ilford Ortho Plus",
    "DeveloperName": "ID-11",
    "Dilution": "1+3",
    "ISO": "80",
    "Film35": "16",
    "Film120": "16",
    "Sheet": "16",
    "Temp": "20C",
    "NotesUrl": "<a href=\"devchart.php?devrow=14153\">[notes]</a>"
  },
  {
    "FilmCode": "Ilford Ortho%",
    "DeveloperCode": null,
    "FilmName": "Ilford Ortho Plus",
    "DeveloperName": "Ilfosol 3",
    "Dilution": "1+9",
    "ISO": "40",
    "Film35": "5",
    "Film120": "5",
    "Sheet": "5",
    "Temp": "20C",
    "NotesUrl": "<a href=\"devchart.php?devrow=16765\">[notes]</a>"
  },
  {
    "FilmCode": "Ilford Ortho%",
    "DeveloperCode": null,
    "FilmName": "Ilford Ortho Plus",
    "DeveloperName": "Ilfosol 3",
    "Dilution": "1+14",
    "ISO": "40",
    "Film35": "7",
    "Film120": "7",
    "Sheet": "7",
    "Temp": "20C",
    "NotesUrl": "<a href=\"devchart.php?devrow=16766\">[notes]</a>"
  },
  {
    "FilmCode": "Ilford Ortho%",
    "DeveloperCode": null,
    "FilmName": "Ilford Ortho Plus",
    "DeveloperName": "Ilfosol 3",
    "Dilution": "1+9",
    "ISO": "80",
    "Film35": "5",
    "Film120": "5",
    "Sheet": "5",
    "Temp": "20C",
    "NotesUrl": "<a href=\"devchart.php?devrow=14885\">[notes]</a>"
  },
  {
    "FilmCode": "Ilford Ortho%",
    "DeveloperCode": null,
    "FilmName": "Ilford Ortho Plus",
    "DeveloperName": "Ilfosol 3",
    "Dilution": "1+14",
    "ISO": "80",
    "Film35": "7",
    "Film120": "7",
    "Sheet": "7",
    "Temp": "20C",
    "NotesUrl": "<a href=\"devchart.php?devrow=16743\">[notes]</a>"
  },
  {
    "FilmCode": "Ilford Ortho%",
    "DeveloperCode": null,
    "FilmName": "Ilford Ortho Plus",
    "DeveloperName": "Ilfotec DD",
    "Dilution": "stock",
    "ISO": "40",
    "Film35": "5:30",
    "Film120": "5:30",
    "Sheet": "5:30",
    "Temp": "24C",
    "NotesUrl": "<a href=\"devchart.php?devrow=2409\">[notes]</a>"
  },
  {
    "FilmCode": "Ilford Ortho%",
    "DeveloperCode": null,
    "FilmName": "Ilford Ortho Plus",
    "DeveloperName": "Ilfotec DD",
    "Dilution": "stock",
    "ISO": "80",
    "Film35": "5:30",
    "Film120": "5:30",
    "Sheet": "5:30",
    "Temp": "24C",
    "NotesUrl": "<a href=\"devchart.php?devrow=2410\">[notes]</a>"
  },
  {
    "FilmCode": "Ilford Ortho%",
    "DeveloperCode": null,
    "FilmName": "Ilford Ortho Plus",
    "DeveloperName": "Ilfotec DD-X",
    "Dilution": "1+4",
    "ISO": "40",
    "Film35": "10:30",
    "Film120": "10:30",
    "Sheet": "10:30",
    "Temp": "20C",
    "NotesUrl": "<a href=\"devchart.php?devrow=2412\">[notes]</a>"
  },
  {
    "FilmCode": "Ilford Ortho%",
    "DeveloperCode": null,
    "FilmName": "Ilford Ortho Plus",
    "DeveloperName": "Ilfotec DD-X",
    "Dilution": "1+4",
    "ISO": "80",
    "Film35": "10:30",
    "Film120": "10:30",
    "Sheet": "10:30",
    "Temp": "20C",
    "NotesUrl": "<a href=\"devchart.php?devrow=2414\">[notes]</a>"
  },
  {
    "FilmCode": "Ilford Ortho%",
    "DeveloperCode": null,
    "FilmName": "Ilford Ortho Plus",
    "DeveloperName": "Ilfotec HC",
    "Dilution": "1+15",
    "ISO": "40",
    "Film35": "4",
    "Film120": "4",
    "Sheet": "4",
    "Temp": "20C",
    "NotesUrl": "<a href=\"devchart.php?devrow=14142\">[notes]</a>"
  },
  {
    "FilmCode": "Ilford Ortho%",
    "DeveloperCode": null,
    "FilmName": "Ilford Ortho Plus",
    "DeveloperName": "Ilfotec HC",
    "Dilution": "1+31",
    "ISO": "40",
    "Film35": "6",
    "Film120": "6",
    "Sheet": "6",
    "Temp": "20C",
    "NotesUrl": "<a href=\"devchart.php?devrow=2415\">[notes]</a>"
  },
  {
    "FilmCode": "Ilford Ortho%",
    "DeveloperCode": null,
    "FilmName": "Ilford Ortho Plus",
    "DeveloperName": "Ilfotec HC",
    "Dilution": "1+15",
    "ISO": "80",
    "Film35": "4",
    "Film120": "4",
    "Sheet": "4",
    "Temp": "20C",
    "NotesUrl": "<a href=\"devchart.php?devrow=14148\">[notes]</a>"
  },
  {
    "FilmCode": "Ilford Ortho%",
    "DeveloperCode": null,
    "FilmName": "Ilford Ortho Plus",
    "DeveloperName": "Ilfotec HC",
    "Dilution": "1+31",
    "ISO": "80",
    "Film35": "6",
    "Film120": "6",
    "Sheet": "6",
    "Temp": "20C",
    "NotesUrl": "<a href=\"devchart.php?devrow=14149\">[notes]</a>"
  },
  {
    "FilmCode": "Ilford Ortho%",
    "DeveloperCode": null,
    "FilmName": "Ilford Ortho Plus",
    "DeveloperName": "Ilfotec LC29",
    "Dilution": "1+9",
    "ISO": "40",
    "Film35": "5",
    "Film120": "5",
    "Sheet": "5",
    "Temp": "20C",
    "NotesUrl": "<a href=\"devchart.php?devrow=2418\">[notes]</a>"
  },
  {
    "FilmCode": "Ilford Ortho%",
    "DeveloperCode": null,
    "FilmName": "Ilford Ortho Plus",
    "DeveloperName": "Ilfotec LC29",
    "Dilution": "1+9",
    "ISO": "40",
    "Film35": "4",
    "Film120": "4",
    "Sheet": "4",
    "Temp": "20C",
    "NotesUrl": "<a href=\"devchart.php?devrow=2417\">[notes]</a>"
  },
  {
    "FilmCode": "Ilford Ortho%",
    "DeveloperCode": null,
    "FilmName": "Ilford Ortho Plus",
    "DeveloperName": "Ilfotec LC29",
    "Dilution": "1+19",
    "ISO": "40",
    "Film35": "6",
    "Film120": "6",
    "Sheet": "6",
    "Temp": "20C",
    "NotesUrl": "<a href=\"devchart.php?devrow=2419\">[notes]</a>"
  },
  {
    "FilmCode": "Ilford Ortho%",
    "DeveloperCode": null,
    "FilmName": "Ilford Ortho Plus",
    "DeveloperName": "Ilfotec LC29",
    "Dilution": "1+19",
    "ISO": "40",
    "Film35": "8",
    "Film120": "8",
    "Sheet": "8",
    "Temp": "20C",
    "NotesUrl": "<a href=\"devchart.php?devrow=2420\">[notes]</a>"
  },
  {
    "FilmCode": "Ilford Ortho%",
    "DeveloperCode": null,
    "FilmName": "Ilford Ortho Plus",
    "DeveloperName": "Ilfotec LC29",
    "Dilution": "1+9",
    "ISO": "80",
    "Film35": "4",
    "Film120": "4",
    "Sheet": "4",
    "Temp": "20C",
    "NotesUrl": "<a href=\"devchart.php?devrow=2421\">[notes]</a>"
  },
  {
    "FilmCode": "Ilford Ortho%",
    "DeveloperCode": null,
    "FilmName": "Ilford Ortho Plus",
    "DeveloperName": "Ilfotec LC29",
    "Dilution": "1+9",
    "ISO": "80",
    "Film35": "5",
    "Film120": "5",
    "Sheet": "5",
    "Temp": "20C",
    "NotesUrl": "<a href=\"devchart.php?devrow=2422\">[notes]</a>"
  },
  {
    "FilmCode": "Ilford Ortho%",
    "DeveloperCode": null,
    "FilmName": "Ilford Ortho Plus",
    "DeveloperName": "Ilfotec LC29",
    "Dilution": "1+19",
    "ISO": "80",
    "Film35": "6",
    "Film120": "6",
    "Sheet": "6",
    "Temp": "20C",
    "NotesUrl": "<a href=\"devchart.php?devrow=2423\">[notes]</a>"
  },
  {
    "FilmCode": "Ilford Ortho%",
    "DeveloperCode": null,
    "FilmName": "Ilford Ortho Plus",
    "DeveloperName": "Ilfotec LC29",
    "Dilution": "1+19",
    "ISO": "80",
    "Film35": "8",
    "Film120": "8",
    "Sheet": "8",
    "Temp": "20C",
    "NotesUrl": "<a href=\"devchart.php?devrow=2424\">[notes]</a>"
  },
  {
    "FilmCode": "Ilford Ortho%",
    "DeveloperCode": null,
    "FilmName": "Ilford Ortho Plus",
    "DeveloperName": "Kalogen",
    "Dilution": "1+50",
    "ISO": "80",
    "Film35": "7:30",
    "Film120": "7:30",
    "Sheet": "7:30",
    "Temp": "20C",
    "NotesUrl": ""
  },
  {
    "FilmCode": "Ilford Ortho%",
    "DeveloperCode": null,
    "FilmName": "Ilford Ortho Plus",
    "DeveloperName": "Microphen",
    "Dilution": "stock",
    "ISO": "40",
    "Film35": "9",
    "Film120": "9",
    "Sheet": "9",
    "Temp": "20C",
    "NotesUrl": "<a href=\"devchart.php?devrow=2425\">[notes]</a>"
  },
  {
    "FilmCode": "Ilford Ortho%",
    "DeveloperCode": null,
    "FilmName": "Ilford Ortho Plus",
    "DeveloperName": "Microphen",
    "Dilution": "1+1",
    "ISO": "40",
    "Film35": "11:30",
    "Film120": "11:30",
    "Sheet": "11:30",
    "Temp": "20C",
    "NotesUrl": "<a href=\"devchart.php?devrow=2426\">[notes]</a>"
  },
  {
    "FilmCode": "Ilford Ortho%",
    "DeveloperCode": null,
    "FilmName": "Ilford Ortho Plus",
    "DeveloperName": "Microphen",
    "Dilution": "1+3",
    "ISO": "40",
    "Film35": "13:30",
    "Film120": "13:30",
    "Sheet": "13:30",
    "Temp": "20C",
    "NotesUrl": "<a href=\"devchart.php?devrow=2427\">[notes]</a>"
  },
  {
    "FilmCode": "Ilford Ortho%",
    "DeveloperCode": null,
    "FilmName": "Ilford Ortho Plus",
    "DeveloperName": "Microphen",
    "Dilution": "stock",
    "ISO": "80",
    "Film35": "9",
    "Film120": "9",
    "Sheet": "9",
    "Temp": "20C",
    "NotesUrl": "<a href=\"devchart.php?devrow=14145\">[notes]</a>"
  },
  {
    "FilmCode": "Ilford Ortho%",
    "DeveloperCode": null,
    "FilmName": "Ilford Ortho Plus",
    "DeveloperName": "Microphen",
    "Dilution": "1+1",
    "ISO": "80",
    "Film35": "11:30",
    "Film120": "11:30",
    "Sheet": "11:30",
    "Temp": "20C",
    "NotesUrl": "<a href=\"devchart.php?devrow=14147\">[notes]</a>"
  },
  {
    "FilmCode": "Ilford Ortho%",
    "DeveloperCode": null,
    "FilmName": "Ilford Ortho Plus",
    "DeveloperName": "Microphen",
    "Dilution": "1+3",
    "ISO": "80",
    "Film35": "13:30",
    "Film120": "13:30",
    "Sheet": "13:30",
    "Temp": "20C",
    "NotesUrl": "<a href=\"devchart.php?devrow=14146\">[notes]</a>"
  },
  {
    "FilmCode": "Ilford Ortho%",
    "DeveloperCode": null,
    "FilmName": "Ilford Ortho Plus",
    "DeveloperName": "Nucleol BF200",
    "Dilution": "20+15+965",
    "ISO": "80",
    "Film35": "9:45",
    "Film120": "9:45",
    "Sheet": "9:45",
    "Temp": "20C",
    "NotesUrl": ""
  },
  {
    "FilmCode": "Ilford Ortho%",
    "DeveloperCode": null,
    "FilmName": "Ilford Ortho Plus",
    "DeveloperName": "Perceptol",
    "Dilution": "stock",
    "ISO": "40",
    "Film35": "13",
    "Film120": "13",
    "Sheet": "13",
    "Temp": "20C",
    "NotesUrl": "<a href=\"devchart.php?devrow=2428\">[notes]</a>"
  },
  {
    "FilmCode": "Ilford Ortho%",
    "DeveloperCode": null,
    "FilmName": "Ilford Ortho Plus",
    "DeveloperName": "Perceptol",
    "Dilution": "stock",
    "ISO": "80",
    "Film35": "13",
    "Film120": "13",
    "Sheet": "13",
    "Temp": "20C",
    "NotesUrl": "<a href=\"devchart.php?devrow=14144\">[notes]</a>"
  },
  {
    "FilmCode": "Ilford Ortho%",
    "DeveloperCode": null,
    "FilmName": "Ilford Ortho Plus",
    "DeveloperName": "PMK",
    "Dilution": "1+2+100",
    "ISO": "40",
    "Film35": "12",
    "Film120": "12",
    "Sheet": "12",
    "Temp": "20C",
    "NotesUrl": ""
  },
  {
    "FilmCode": "Ilford Ortho%",
    "DeveloperCode": null,
    "FilmName": "Ilford Ortho Plus",
    "DeveloperName": "POTA",
    "Dilution": "stock",
    "ISO": "40",
    "Film35": "9:30",
    "Film120": "9:30",
    "Sheet": "9:30",
    "Temp": "20C",
    "NotesUrl": "<a href=\"devchart.php?devrow=8664\">[notes]</a>"
  },
  {
    "FilmCode": "Ilford Ortho%",
    "DeveloperCode": null,
    "FilmName": "Ilford Ortho Plus",
    "DeveloperName": "POTA",
    "Dilution": "stock",
    "ISO": "80",
    "Film35": "9:30",
    "Film120": "9:30",
    "Sheet": "9:30",
    "Temp": "20C",
    "NotesUrl": "<a href=\"devchart.php?devrow=8663\">[notes]</a>"
  },
  {
    "FilmCode": "Ilford Ortho%",
    "DeveloperCode": null,
    "FilmName": "Ilford Ortho Plus",
    "DeveloperName": "PQ Universal",
    "Dilution": "1+9",
    "ISO": "50",
    "Film35": "12",
    "Film120": "12",
    "Sheet": "12",
    "Temp": "20C",
    "NotesUrl": ""
  },
  {
    "FilmCode": "Ilford Ortho%",
    "DeveloperCode": null,
    "FilmName": "Ilford Ortho Plus",
    "DeveloperName": "Pyrocat-HD",
    "Dilution": "1+1+100",
    "ISO": "80",
    "Film35": "14:30",
    "Film120": "14:30",
    "Sheet": "14:30",
    "Temp": "20C",
    "NotesUrl": ""
  },
  {
    "FilmCode": "Ilford Ortho%",
    "DeveloperCode": null,
    "FilmName": "Ilford Ortho Plus",
    "DeveloperName": "Rodinal",
    "Dilution": "1+100",
    "ISO": "40",
    "Film35": "10",
    "Film120": "10",
    "Sheet": "10",
    "Temp": "20C",
    "NotesUrl": "<a href=\"devchart.php?devrow=2429\">[notes]</a>"
  },
  {
    "FilmCode": "Ilford Ortho%",
    "DeveloperCode": null,
    "FilmName": "Ilford Ortho Plus",
    "DeveloperName": "Rodinal",
    "Dilution": "1+25",
    "ISO": "80",
    "Film35": "7",
    "Film120": "7",
    "Sheet": "7",
    "Temp": "20C",
    "NotesUrl": ""
  },
  {
    "FilmCode": "Ilford Ortho%",
    "DeveloperCode": null,
    "FilmName": "Ilford Ortho Plus",
    "DeveloperName": "Rodinal",
    "Dilution": "1+50",
    "ISO": "80",
    "Film35": "15",
    "Film120": "15",
    "Sheet": "15",
    "Temp": "20C",
    "NotesUrl": ""
  },
  {
    "FilmCode": "Ilford Ortho%",
    "DeveloperCode": null,
    "FilmName": "Ilford Ortho Plus",
    "DeveloperName": "Spur SHADOWmax",
    "Dilution": "1+2+47",
    "ISO": "80",
    "Film35": "9",
    "Film120": "9",
    "Sheet": "9",
    "Temp": "20C",
    "NotesUrl": "<a href=\"devchart.php?devrow=15112\">[notes]</a>"
  },
  {
    "FilmCode": "Ilford Ortho%",
    "DeveloperCode": null,
    "FilmName": "Ilford Ortho Plus",
    "DeveloperName": "Spur SHADOWmax",
    "Dilution": "2+9+79",
    "ISO": "125",
    "Film35": "10",
    "Film120": "10",
    "Sheet": "10",
    "Temp": "20C",
    "NotesUrl": "<a href=\"devchart.php?devrow=15113\">[notes]</a>"
  },
  {
    "FilmCode": "Ilford Ortho%",
    "DeveloperCode": null,
    "FilmName": "Ilford Ortho Plus",
    "DeveloperName": "Spur SHADOWmax",
    "Dilution": "5+19+16",
    "ISO": "200",
    "Film35": "12",
    "Film120": "12",
    "Sheet": "12",
    "Temp": "20C",
    "NotesUrl": "<a href=\"devchart.php?devrow=15114\">[notes]</a>"
  },
  {
    "FilmCode": "Ilford Ortho%",
    "DeveloperCode": null,
    "FilmName": "Ilford Ortho Plus",
    "DeveloperName": "Spur SHADOWmax",
    "Dilution": "10+31+269",
    "ISO": "320",
    "Film35": "15",
    "Film120": "15",
    "Sheet": "15",
    "Temp": "20C",
    "NotesUrl": "<a href=\"devchart.php?devrow=15115\">[notes]</a>"
  },
  {
    "FilmCode": "Ilford Ortho%",
    "DeveloperCode": null,
    "FilmName": "Ilford Ortho Plus",
    "DeveloperName": "TMax Dev",
    "Dilution": "1+4",
    "ISO": "100",
    "Film35": "7:30",
    "Film120": "7:30",
    "Sheet": "7:30",
    "Temp": "20C",
    "NotesUrl": ""
  },
  {
    "FilmCode": "Ilford Ortho%",
    "DeveloperCode": null,
    "FilmName": "Ilford Ortho Plus",
    "DeveloperName": "TMax Dev",
    "Dilution": "1+9",
    "ISO": "100",
    "Film35": "15",
    "Film120": "15",
    "Sheet": "15",
    "Temp": "20C",
    "NotesUrl": ""
  },
  {
    "FilmCode": "Ilford Ortho%",
    "DeveloperCode": null,
    "FilmName": "Ilford Ortho Plus",
    "DeveloperName": "XT-3",
    "Dilution": "stock",
    "ISO": "80",
    "Film35": "7:30",
    "Film120": "7:30",
    "Sheet": "7:30",
    "Temp": "20C",
    "NotesUrl": "<a href=\"devchart.php?devrow=15767\">[notes]</a>"
  },
  {
    "FilmCode": "Ilford Ortho%",
    "DeveloperCode": null,
    "FilmName": "Ilford Ortho Plus",
    "DeveloperName": "XT-3",
    "Dilution": "1+1",
    "ISO": "80",
    "Film35": "10",
    "Film120": "10",
    "Sheet": "10",
    "Temp": "20C",
    "NotesUrl": ""
  },
  {
    "FilmCode": "Ilford Ortho%",
    "DeveloperCode": null,
    "FilmName": "Ilford Ortho Plus",
    "DeveloperName": "Xtol",
    "Dilution": "stock",
    "ISO": "80",
    "Film35": "7:30",
    "Film120": "7:30",
    "Sheet": "7:30",
    "Temp": "20C",
    "NotesUrl": "<a href=\"devchart.php?devrow=14555\">[notes]</a>"
  },
  {
    "FilmCode": "Ilford Ortho%",
    "DeveloperCode": null,
    "FilmName": "Ilford Ortho Plus",
    "DeveloperName": "Xtol",
    "Dilution": "1+1",
    "ISO": "80",
    "Film35": "10",
    "Film120": "10",
    "Sheet": "10",
    "Temp": "20C",
    "NotesUrl": ""
  }
]